xia_engine_firestore/__init__.py
xia_engine_firestore/engine.cpython-310-darwin.so
xia_engine_firestore-0.3.8.dist-info/LICENSE.txt
xia_engine_firestore-0.3.8.dist-info/METADATA
xia_engine_firestore-0.3.8.dist-info/WHEEL
xia_engine_firestore-0.3.8.dist-info/top_level.txt
xia_engine_firestore-0.3.8.dist-info/RECORD
