Metadata-Version: 2.1
Name: xia-engine-firestore
Version: 0.3.8
Summary: UNKNOWN
Home-page: https://develop.x-i-a.com/docs/xia-engine-firestore/0.3.8/index.html
Author: X-I-A
Author-email: admin@x-i-a.com
License: UNKNOWN
Platform: UNKNOWN
Requires-Python: >=3.9
License-File: LICENSE.txt
Requires-Dist: google-cloud-firestore
Requires-Dist: xia-engine
